isEven/__init__.py
isEven/is_even.py
IsNumberEven-1.1.0.dist-info/METADATA
IsNumberEven-1.1.0.dist-info/WHEEL
IsNumberEven-1.1.0.dist-info/top_level.txt
IsNumberEven-1.1.0.dist-info/RECORD
