Metadata-Version: 2.1
Name: IsNumberEven
Version: 1.1.0
Summary: Return true if the given number is even.
Home-page: https://github.com/programadriano/is-even
Author: Thiago S Adriano
Author-email: prof.thiagoadriano@gmail.com
License: MIT
